infragenie/genie.py
infragenie-0.1.5.dist-info/LICENSE.txt
infragenie-0.1.5.dist-info/METADATA
infragenie-0.1.5.dist-info/WHEEL
infragenie-0.1.5.dist-info/entry_points.txt
infragenie-0.1.5.dist-info/top_level.txt
infragenie-0.1.5.dist-info/RECORD
