Metadata-Version: 2.1
Name: infragenie
Version: 0.1.5
Summary: decompose your terraform with dependency injection
Home-page: https://github.com/diggerhq/infragenie
Author: Mohamed Habib
Author-email: mo@digger.dev
License: UNKNOWN
Platform: UNKNOWN
License-File: LICENSE.txt
Requires-Dist: python-hcl2 (==3.0.1)
Requires-Dist: click (==7.1.2)
Requires-Dist: rich (==10.9.0)
